zengin/__init__.py
zengin/prep.py
zengin/zengin.py
zengin/zengindata.json
pyzengin-0.1.7.dist-info/LICENSE
pyzengin-0.1.7.dist-info/METADATA
pyzengin-0.1.7.dist-info/WHEEL
pyzengin-0.1.7.dist-info/RECORD
