Metadata-Version: 2.1
Name: pyzengin
Version: 0.1.7
Summary: Japanese Bank and Branch Code Data
Author: Deyong Zheng
Author-email: zhengdy@me.com
Requires-Python: >=3.7,<4.0
Classifier: Programming Language :: Python :: 3
Classifier: Programming Language :: Python :: 3.7
Classifier: Programming Language :: Python :: 3.8
Classifier: Programming Language :: Python :: 3.9
Classifier: Programming Language :: Python :: 3.10
Classifier: Programming Language :: Python :: 3.11
